snitize/__init__.py
snitizer-1.0.0.dist-info/METADATA
snitizer-1.0.0.dist-info/WHEEL
snitizer-1.0.0.dist-info/top_level.txt
snitizer-1.0.0.dist-info/RECORD
