Metadata-Version: 2.4
Name: snitizer
Version: 1.0.0
Summary: Minimal library for sanitizing and validating user input strings.
Author-email: Sanitizer <laporcamion16@gmail.com>
License: MIT
Keywords: security,sanitize,input,validation,strings,sntz
Classifier: Development Status :: 4 - Beta
Classifier: Intended Audience :: Developers
Classifier: Topic :: Security
Classifier: Topic :: Software Development :: Libraries :: Python Modules
Classifier: Programming Language :: Python :: 3
Classifier: License :: OSI Approved :: MIT License
Classifier: Operating System :: OS Independent
Requires-Python: >=3.6
Requires-Dist: requests>=2.0
